py_dbutils/__init__.py
py_dbutils/parents.py
py_dbutils/sed_comment.sh
py_dbutils/setup.py
py_dbutils/utils.py
py_dbutils/rdbms/__init__.py
py_dbutils/rdbms/bigquery.py
py_dbutils/rdbms/msaccess.py
py_dbutils/rdbms/mssql.py
py_dbutils/rdbms/mysql.py
py_dbutils/rdbms/postgres.py
py_dbutils/rdbms/sqlite.py
py_dbutils/rdbms/jdbc_jar/commons-lang-2.6.jar
py_dbutils/rdbms/jdbc_jar/commons-logging-1.1.3.jar
py_dbutils/rdbms/jdbc_jar/hsqldb-2.3.1.jar
py_dbutils/rdbms/jdbc_jar/jackcess-2.1.6.jar
py_dbutils/rdbms/jdbc_jar/ucanaccess-4.0.2.jar
py_dbutils/restdb/bigquery.py
py_dbutils-0.4.28.dist-info/AUTHORS.rst
py_dbutils-0.4.28.dist-info/LICENSE.txt
py_dbutils-0.4.28.dist-info/METADATA
py_dbutils-0.4.28.dist-info/WHEEL
py_dbutils-0.4.28.dist-info/top_level.txt
py_dbutils-0.4.28.dist-info/RECORD
