Metadata-Version: 2.1
Name: py-dbutils
Version: 0.4.28
Summary: libraries to move data between different databases
Home-page: https://github.com/hung135/py-dbutils/
Author: hnguyen
Author-email: hung135@hotmail.com
License: mit
Platform: any
Classifier: Development Status :: 4 - Beta
Classifier: Programming Language :: Python
Requires-Python: >=3.4
Requires-Dist: sqlalchemy
Requires-Dist: pandas
Requires-Dist: psycopg2-binary
Provides-Extra: testing
Requires-Dist: pytest ; extra == 'testing'
Requires-Dist: pytest-cov ; extra == 'testing'
